<?xml version='1.0' encoding='utf-8'?>
<container xmlns="https://open.law/schemas/library" xmlns:cache="https://open.law/schemas/cache" xmlns:citations="https://open.law/schemas/citations" xmlns:macro="https://open.law/schemas/macro" xmlns:xs="http://www.w3.org/2001/XMLSchema" xmlns:xsl="http://www.w3.org/1999/XSL/Transform" xmlns:codified="https://open.law/schemas/codified" xmlns:codify="https://open.law/schemas/codify" xmlns:xi="http://www.w3.org/2001/XInclude">
  <prefix>Chapter</prefix>
  <num>03</num>
  <heading>Driver Education Programs</heading>
  <reason>Repealed</reason>
  <annotations>
    <annotation managed="false" type="History" subtype="Administrative History" dest="container" effective="1970-01-08">Effective date: January 8, 1970</annotation>
    <annotation managed="false" type="History" subtype="Administrative History" dest="container" effective="1975-07-23">Chapter revised effective July 23, 1975 (2:16 Md. R. 1138)</annotation>
    <annotation managed="false" type="History" subtype="Administrative History" dest="container" effective="1981-08-28">Regulations <cite path="|13A|04|03|.03">.03</cite>—<cite path="|13A|04|03|.05">.05</cite>, .10 amended as an emergency provision effective August 28, 1981 (8:19 Md. R. 1561); emergency status expired January 16, 1982 (Emergency provisions are temporary and not printed in COMAR)</annotation>
    <annotation managed="false" type="History" subtype="Administrative History" dest="container" effective="1982-01-18">Regulations .03; .04A, B; .05; .09K; and .10D amended effective January 18, 1982 (9:1 Md. R. 23)</annotation>
    <annotation managed="false" type="History" subtype="Administrative History" dest="container" effective="1989-04-03" discontinuity="true">Regulations <cite path="|13A|04|03|.01">.01</cite>—<cite path="|13A|04|03|.13">.13</cite> repealed and new Regulations <cite path="|13A|04|03|.01">.01</cite>—<cite path="|13A|04|03|.11">.11</cite> adopted effective April 3, 1989 (16:6 Md. R. 728)</annotation>
    <annotation managed="false" type="History" subtype="Administrative History" dest="container" effective="1994-07-04"><cite path="|13A|04|03|.03|G.">Regulation .03G</cite> amended effective July 4, 1994 (21:13 Md. R. 1159)</annotation>
    <annotation managed="false" type="History" subtype="Administrative History" dest="container" effective="2017-02-13" discontinuity="true">Chapter repealed effective February 13, 2017 (44:3 Md. R. 189)</annotation>
  </annotations>
</container>
